{
    "blocks": {
        "desire:concrete_bricks": {
            "desire:white_concrete_bricks": "white",
            "desire:orange_concrete_bricks": "orange",
            "desire:magenta_concrete_bricks": "magenta",
            "desire:light_blue_concrete_bricks": "light_blue",
            "desire:yellow_concrete_bricks": "yellow",
            "desire:lime_concrete_bricks": "lime",
            "desire:pink_concrete_bricks": "pink",
            "desire:gray_concrete_bricks": "gray",
            "desire:light_gray_concrete_bricks": "light_gray",
            "desire:cyan_concrete_bricks": "cyan",
            "desire:purple_concrete_bricks": "purple",
            "desire:blue_concrete_bricks": "blue",
            "desire:brown_concrete_bricks": "brown",
            "desire:green_concrete_bricks": "green",
            "desire:red_concrete_bricks": "red",
            "desire:black_concrete_bricks": "black"
        },
        "desire:concrete_brick_stairs": {
            "desire:white_concrete_brick_stairs": "white",
            "desire:orange_concrete_brick_stairs": "orange",
            "desire:magenta_concrete_brick_stairs": "magenta",
            "desire:light_blue_concrete_brick_stairs": "light_blue",
            "desire:yellow_concrete_brick_stairs": "yellow",
            "desire:lime_concrete_brick_stairs": "lime",
            "desire:pink_concrete_brick_stairs": "pink",
            "desire:gray_concrete_brick_stairs": "gray",
            "desire:light_gray_concrete_brick_stairs": "light_gray",
            "desire:cyan_concrete_brick_stairs": "cyan",
            "desire:purple_concrete_brick_stairs": "purple",
            "desire:blue_concrete_brick_stairs": "blue",
            "desire:brown_concrete_brick_stairs": "brown",
            "desire:green_concrete_brick_stairs": "green",
            "desire:red_concrete_brick_stairs": "red",
            "desire:black_concrete_brick_stairs": "black"
        },
        "desire:concrete_brick_slab": {
            "desire:white_concrete_brick_slab": "white",
            "desire:orange_concrete_brick_slab": "orange",
            "desire:magenta_concrete_brick_slab": "magenta",
            "desire:light_blue_concrete_brick_slab": "light_blue",
            "desire:yellow_concrete_brick_slab": "yellow",
            "desire:lime_concrete_brick_slab": "lime",
            "desire:pink_concrete_brick_slab": "pink",
            "desire:gray_concrete_brick_slab": "gray",
            "desire:light_gray_concrete_brick_slab": "light_gray",
            "desire:cyan_concrete_brick_slab": "cyan",
            "desire:purple_concrete_brick_slab": "purple",
            "desire:blue_concrete_brick_slab": "blue",
            "desire:brown_concrete_brick_slab": "brown",
            "desire:green_concrete_brick_slab": "green",
            "desire:red_concrete_brick_slab": "red",
            "desire:black_concrete_brick_slab": "black"
        },
        "desire:concrete_brick_wall": {
            "desire:white_concrete_brick_wall": "white",
            "desire:orange_concrete_brick_wall": "orange",
            "desire:magenta_concrete_brick_wall": "magenta",
            "desire:light_blue_concrete_brick_wall": "light_blue",
            "desire:yellow_concrete_brick_wall": "yellow",
            "desire:lime_concrete_brick_wall": "lime",
            "desire:pink_concrete_brick_wall": "pink",
            "desire:gray_concrete_brick_wall": "gray",
            "desire:light_gray_concrete_brick_wall": "light_gray",
            "desire:cyan_concrete_brick_wall": "cyan",
            "desire:purple_concrete_brick_wall": "purple",
            "desire:blue_concrete_brick_wall": "blue",
            "desire:brown_concrete_brick_wall": "brown",
            "desire:green_concrete_brick_wall": "green",
            "desire:red_concrete_brick_wall": "red",
            "desire:black_concrete_brick_wall": "black"
        },
        "desire:terracotta_mosaic": {
            "desire:white_terracotta_mosaic": "white",
            "desire:orange_terracotta_mosaic": "orange",
            "desire:magenta_terracotta_mosaic": "magenta",
            "desire:light_blue_terracotta_mosaic": "light_blue",
            "desire:yellow_terracotta_mosaic": "yellow",
            "desire:lime_terracotta_mosaic": "lime",
            "desire:pink_terracotta_mosaic": "pink",
            "desire:gray_terracotta_mosaic": "gray",
            "desire:light_gray_terracotta_mosaic": "light_gray",
            "desire:cyan_terracotta_mosaic": "cyan",
            "desire:purple_terracotta_mosaic": "purple",
            "desire:blue_terracotta_mosaic": "blue",
            "desire:brown_terracotta_mosaic": "brown",
            "desire:green_terracotta_mosaic": "green",
            "desire:red_terracotta_mosaic": "red",
            "desire:black_terracotta_mosaic": "black"
        },
        "desire:terracotta_mosaic_stairs": {
            "desire:white_terracotta_mosaic_stairs": "white",
            "desire:orange_terracotta_mosaic_stairs": "orange",
            "desire:magenta_terracotta_mosaic_stairs": "magenta",
            "desire:light_blue_terracotta_mosaic_stairs": "light_blue",
            "desire:yellow_terracotta_mosaic_stairs": "yellow",
            "desire:lime_terracotta_mosaic_stairs": "lime",
            "desire:pink_terracotta_mosaic_stairs": "pink",
            "desire:gray_terracotta_mosaic_stairs": "gray",
            "desire:light_gray_terracotta_mosaic_stairs": "light_gray",
            "desire:cyan_terracotta_mosaic_stairs": "cyan",
            "desire:purple_terracotta_mosaic_stairs": "purple",
            "desire:blue_terracotta_mosaic_stairs": "blue",
            "desire:brown_terracotta_mosaic_stairs": "brown",
            "desire:green_terracotta_mosaic_stairs": "green",
            "desire:red_terracotta_mosaic_stairs": "red",
            "desire:black_terracotta_mosaic_stairs": "black"
        },
        "desire:terracotta_mosaic_slab": {
            "desire:white_terracotta_mosaic_slab": "white",
            "desire:orange_terracotta_mosaic_slab": "orange",
            "desire:magenta_terracotta_mosaic_slab": "magenta",
            "desire:light_blue_terracotta_mosaic_slab": "light_blue",
            "desire:yellow_terracotta_mosaic_slab": "yellow",
            "desire:lime_terracotta_mosaic_slab": "lime",
            "desire:pink_terracotta_mosaic_slab": "pink",
            "desire:gray_terracotta_mosaic_slab": "gray",
            "desire:light_gray_terracotta_mosaic_slab": "light_gray",
            "desire:cyan_terracotta_mosaic_slab": "cyan",
            "desire:purple_terracotta_mosaic_slab": "purple",
            "desire:blue_terracotta_mosaic_slab": "blue",
            "desire:brown_terracotta_mosaic_slab": "brown",
            "desire:green_terracotta_mosaic_slab": "green",
            "desire:red_terracotta_mosaic_slab": "red",
            "desire:black_terracotta_mosaic_slab": "black"
        },
        "desire:terracotta_mosaic_wall": {
            "desire:white_terracotta_mosaic_wall": "white",
            "desire:orange_terracotta_mosaic_wall": "orange",
            "desire:magenta_terracotta_mosaic_wall": "magenta",
            "desire:light_blue_terracotta_mosaic_wall": "light_blue",
            "desire:yellow_terracotta_mosaic_wall": "yellow",
            "desire:lime_terracotta_mosaic_wall": "lime",
            "desire:pink_terracotta_mosaic_wall": "pink",
            "desire:gray_terracotta_mosaic_wall": "gray",
            "desire:light_gray_terracotta_mosaic_wall": "light_gray",
            "desire:cyan_terracotta_mosaic_wall": "cyan",
            "desire:purple_terracotta_mosaic_wall": "purple",
            "desire:blue_terracotta_mosaic_wall": "blue",
            "desire:brown_terracotta_mosaic_wall": "brown",
            "desire:green_terracotta_mosaic_wall": "green",
            "desire:red_terracotta_mosaic_wall": "red",
            "desire:black_terracotta_mosaic_wall": "black"
        }
    },
    "items": {}
}