{
  "parent": "minecraft:recipes/root",
  "criteria": {
    "has_indigo_candle": {
      "conditions": {
        "items": [
          {
            "items": [
              "dye_depot:indigo_candle"
            ]
          }
        ]
      },
      "trigger": "minecraft:inventory_changed"
    },
    "has_the_recipe": {
      "conditions": {
        "recipe": "minecraft:adorn/indigo_candlelit_lantern"
      },
      "trigger": "minecraft:recipe_unlocked"
    }
  },
  "requirements": [
    [
      "has_indigo_candle",
      "has_the_recipe"
    ]
  ],
  "rewards": {
    "recipes": [
      "minecraft:adorn/indigo_candlelit_lantern"
    ]
  },
  "sends_telemetry_event": false
}